libtaxii/__init__.py
libtaxii/clients.py
libtaxii/common.py
libtaxii/constants.py
libtaxii/messages.py
libtaxii/messages_10.py
libtaxii/messages_11.py
libtaxii/taxii_default_query.py
libtaxii/validation.py
libtaxii/version.py
libtaxii/scripts/__init__.py
libtaxii/scripts/collection_information_client.py
libtaxii/scripts/discovery_client.py
libtaxii/scripts/discovery_client_10.py
libtaxii/scripts/feed_information_client_10.py
libtaxii/scripts/fulfillment_client.py
libtaxii/scripts/inbox_client.py
libtaxii/scripts/inbox_client_10.py
libtaxii/scripts/poll_client.py
libtaxii/scripts/poll_client_10.py
libtaxii/scripts/query_client.py
libtaxii/test/__init__.py
libtaxii/test/argument_parser_test.py
libtaxii/test/clients_test.py
libtaxii/test/messages_10_test.py
libtaxii/test/messages_11_test.py
libtaxii/test/test_clients.py
libtaxii/test/test_xml_encoding.py
libtaxii/test/to_text_11_test.py
libtaxii/test/validation_test.py
libtaxii/xsd/TAXII_DefaultQuery_Schema.xsd
libtaxii/xsd/TAXII_XMLMessageBinding_Schema.xsd
libtaxii/xsd/TAXII_XMLMessageBinding_Schema_11.xsd
libtaxii/xsd/xmldsig-core-schema.xsd
libtaxii-1.1.119.data/scripts/collection_information_client.py
libtaxii-1.1.119.data/scripts/discovery_client.py
libtaxii-1.1.119.data/scripts/discovery_client_10.py
libtaxii-1.1.119.data/scripts/feed_information_client_10.py
libtaxii-1.1.119.data/scripts/fulfillment_client.py
libtaxii-1.1.119.data/scripts/inbox_client.py
libtaxii-1.1.119.data/scripts/inbox_client_10.py
libtaxii-1.1.119.data/scripts/poll_client.py
libtaxii-1.1.119.data/scripts/poll_client_10.py
libtaxii-1.1.119.data/scripts/query_client.py
libtaxii-1.1.119.dist-info/LICENSE.txt
libtaxii-1.1.119.dist-info/METADATA
libtaxii-1.1.119.dist-info/WHEEL
libtaxii-1.1.119.dist-info/entry_points.txt
libtaxii-1.1.119.dist-info/top_level.txt
libtaxii-1.1.119.dist-info/RECORD
