Metadata-Version: 2.1
Name: libtaxii
Version: 1.1.119
Summary: TAXII 1.X Library.
Home-page: https://taxiiproject.github.io/
Author: The MITRE Corporation
Author-email: taxii@mitre.org
License: BSD
Project-URL: Source Code, https://github.com/TAXIIProject/libtaxii/
Project-URL: Documentation, https://libtaxii.readthedocs.io/
Project-URL: Bug Tracker, https://github.com/TAXIIProject/libtaxii/issues/
Keywords: taxii libtaxii
Platform: UNKNOWN
Classifier: Development Status :: 5 - Production/Stable
Classifier: Intended Audience :: Developers
Classifier: License :: OSI Approved :: BSD License
Classifier: Operating System :: OS Independent
Classifier: Programming Language :: Python :: 2
Classifier: Programming Language :: Python :: 2.6
Classifier: Programming Language :: Python :: 2.7
Classifier: Programming Language :: Python :: 3
Classifier: Programming Language :: Python :: 3.3
Classifier: Programming Language :: Python :: 3.4
Classifier: Programming Language :: Python :: 3.5
Classifier: Programming Language :: Python :: 3.6
Classifier: Programming Language :: Python :: 3.7
Classifier: Programming Language :: Python :: 3.8
Requires-Dist: python-dateutil (>=1.4.1)
Requires-Dist: six (>=1.9.0)
Requires-Dist: lxml (>=2.2.3)
